{
    "version": "0.0.2",
    "description": "Cheat Sheets on Desktop",
    "homepage": "https://github.com/mvrpl/Desktop-Cheat-Sheet",
    "license": "MIT",
    "architecture": {
        "64bit": {
            "url": "https://github.com/mvrpl/Desktop-Cheat-Sheet/releases/download/v0.0.2/Desktop-Cheat-Sheet-amd64-installer.exe",
            "hash": "2c8bf5e34e3fc49a163e87d9b20841362b82371452cd955e1f910057effd8205"
        }
    },
    "depends": "chsht",
    "installer": {
        "script": [
            "Move-Item -Path \"$dir\\Desktop-Cheat-Sheet-amd64-installer.exe\" -Destination \"$dir\\setup.exe\"",
            "Start-Process \"$dir\\setup.exe\" -ArgumentList '/S' -Wait | Out-Null",
            "Remove-Item \"$dir\\setup.exe\""
        ]
    },
    "uninstaller": {
        "script": "Start-Process \"$([System.Environment]::GetFolderPath('ProgramFiles'))\\Desktop-Cheat-Sheet\\Desktop-Cheat-Sheet\\uninstall.exe\" -ArgumentList '/S' -Wait | Out-Null"
    },
    "checkver": "github",
    "autoupdate": {
        "architecture": {
            "64bit": {
                "url": "https://github.com/mvrpl/Desktop-Cheat-Sheet/releases/download/v$version/Desktop-Cheat-Sheet-amd64-installer.exe"
            }
        }
    }
}
